AUTHORS
LICENSE
MANIFEST.in
README
setup.cfg
setup.py
django_hgwebproxy.egg-info/PKG-INFO
django_hgwebproxy.egg-info/SOURCES.txt
django_hgwebproxy.egg-info/dependency_links.txt
django_hgwebproxy.egg-info/top_level.txt
docs/NOTES
docs/apache_conf/django.wsgi
example/__init__.py
example/database.sqlite
example/manage.py
example/settings.py
example/urls.py
example/views.py
example/static/background.png
example/static/coal-file.png
example/static/coal-folder.png
example/static/excanvas.js
example/static/graph.js
example/static/hgicon.png
example/static/hglogo.png
example/static/style-monoblue.css
example/templates/registration/login.html
example/templates/registration/logout.html
hgwebproxy/__init__.py
hgwebproxy/admin.py
hgwebproxy/models.py
hgwebproxy/proxy.py
hgwebproxy/settings.py
hgwebproxy/urls.py
hgwebproxy/utils.py
hgwebproxy/views.py
hgwebproxy/templates/admin/hgwebproxy/repo.html
hgwebproxy/templates/admin/hgwebproxy/repo_list.html
hgwebproxy/templates/admin/hgwebproxy/repository/change_list.html
hgwebproxy/templates/monoblue_plain/changelog.tmpl
hgwebproxy/templates/monoblue_plain/changelogentry.tmpl
hgwebproxy/templates/monoblue_plain/changeset.tmpl
hgwebproxy/templates/monoblue_plain/error.tmpl
hgwebproxy/templates/monoblue_plain/fileannotate.tmpl
hgwebproxy/templates/monoblue_plain/filediff.tmpl
hgwebproxy/templates/monoblue_plain/filelog.tmpl
hgwebproxy/templates/monoblue_plain/filerevision.tmpl
hgwebproxy/templates/monoblue_plain/footer.tmpl
hgwebproxy/templates/monoblue_plain/graph.tmpl
hgwebproxy/templates/monoblue_plain/header.tmpl
hgwebproxy/templates/monoblue_plain/index.tmpl
hgwebproxy/templates/monoblue_plain/manifest.tmpl
hgwebproxy/templates/monoblue_plain/map
hgwebproxy/templates/monoblue_plain/notfound.tmpl
hgwebproxy/templates/monoblue_plain/search.tmpl
hgwebproxy/templates/monoblue_plain/shortlog.tmpl
hgwebproxy/templates/monoblue_plain/summary.tmpl
hgwebproxy/templates/monoblue_plain/tags.tmpl