Metadata-Version: 1.0
Name: django-hgwebproxy
Version: 0.2.0
Summary: Django-hgwebproxy is an app to use and manage mercurial repositories within the django admin interface
Home-page: http://bitbucket.org/mariocesar/django-hgweproxy/
Author: Mario C&Atilde;&copy;sar Se&Atilde;&plusmn;oranis Ayala
Author-email: mariocesar.sa@openit.com.bo
License: GPL
Keywords: django mercurial hg bitbucket webapp
Platform: UNKNOWN
Classifier: Development Status :: 3 - Alpha
Classifier: Environment :: Web Environment
Classifier: Framework :: Django
Classifier: Intended Audience :: Developers
Classifier: Intended Audience :: Developers
Classifier: License :: OSI Approved :: GNU General Public License (GPL)
Classifier: Natural Language :: English
Classifier: Natural Language :: Spanish
Classifier: Operating System :: OS Independent
Classifier: Programming Language :: Python
